{
  "updated": "2026-07-03T20:03",
  "temp_air": "16",
  "meteo_picto": "sun",
  "meteo_label": "Ciel degage",
  "temp_eau": "NC",
  "vent_kmh": "11",
  "vent_deg": "324",
  "vent_cardinal": "NO",
  "uv": "5.3",
  "uv_label": "Modere",
  "lever": "06:29",
  "coucher": "21:50",
  "houle_m": "0.82",
  "houle_periode": "7.5",
  "marees": [
    {
      "type": "Basse",
      "heure": "01h15"
    },
    {
      "type": "Haute",
      "heure": "07h22"
    },
    {
      "type": "Basse",
      "heure": "13h22"
    },
    {
      "type": "Haute",
      "heure": "19h38"
    }
  ],
  "maree_coef": "",
  "maree_coef_am": "",
  "maree_coef_pm": "",
  "drapeau": "nc",
  "surv_label": "Baignade non surveillee",
  "transports": {
    "bayonne": [
      "07:50",
      "11:17",
      "14:16"
    ],
    "dax": [
      "08:14",
      "09:37",
      "14:37"
    ]
  }
}