{
  "updated": "2026-07-12T14:02",
  "temp_air": "36",
  "meteo_picto": "cloud-sun",
  "meteo_label": "Ciel degage",
  "temp_eau": "NC",
  "vent_kmh": "17",
  "vent_deg": "70",
  "vent_cardinal": "ENE",
  "uv": "6.2",
  "uv_label": "Eleve",
  "lever": "06:36",
  "coucher": "21:46",
  "houle_m": "0.54",
  "houle_periode": "9.2",
  "marees": [
    {
      "type": "Haute",
      "heure": "03h11"
    },
    {
      "type": "Basse",
      "heure": "09h07"
    },
    {
      "type": "Haute",
      "heure": "15h37"
    },
    {
      "type": "Basse",
      "heure": "21h45"
    }
  ],
  "maree_coef": "65 / 70",
  "maree_coef_am": "65",
  "maree_coef_pm": "70",
  "drapeau": "nc",
  "surv_label": "Baignade non surveillee",
  "transports": {
    "bayonne": [
      "17:17",
      "18:17",
      "20:54"
    ],
    "dax": [
      "17:42",
      "18:28",
      "20:51"
    ]
  },
  "bus": {
    "plage": [
      "16:38",
      "16:52",
      "17:08"
    ],
    "ondres_bourg": [
      "16:46",
      "16:52",
      "17:01"
    ],
    "st_martin": [
      "16:02",
      "16:15",
      "17:02"
    ],
    "bayonne": [
      "16:40",
      "17:00",
      "17:10"
    ],
    "fetes_bayonne": []
  }
}