{
  "updated": "2026-06-30T09:40",
  "temp_air": "16",
  "meteo_picto": "sun",
  "meteo_label": "Couvert",
  "temp_eau": "NC",
  "vent_kmh": "12",
  "vent_deg": "317",
  "vent_cardinal": "NO",
  "uv": "5.5",
  "uv_label": "Modere",
  "lever": "06:28",
  "coucher": "21:51",
  "houle_m": "1.64",
  "houle_periode": "10.4",
  "marees": [
    {
      "type": "Haute",
      "heure": "05h40"
    },
    {
      "type": "Basse",
      "heure": "11h39"
    },
    {
      "type": "Haute",
      "heure": "17h50"
    },
    {
      "type": "Basse",
      "heure": "00h05"
    }
  ],
  "maree_coef": "",
  "maree_coef_am": "",
  "maree_coef_pm": "",
  "drapeau": "nc",
  "surv_label": "Baignade non surveillee",
  "transports": {
    "bayonne": [
      "13:17",
      "17:17",
      "17:43"
    ],
    "dax": [
      "14:37",
      "17:12",
      "18:38"
    ]
  }
}