{
  "updated": "2026-05-18T12:14",
  "temp_air": "12",
  "meteo_picto": "cloud-sun",
  "meteo_label": "Couvert",
  "temp_eau": "NC",
  "vent_kmh": "9",
  "vent_deg": "313",
  "vent_cardinal": "NO",
  "uv": "6.8",
  "uv_label": "Eleve",
  "lever": "06:37",
  "coucher": "21:26",
  "houle_m": "1.54",
  "houle_periode": "11.1",
  "marees": [
    {
      "type": "Haute",
      "heure": "06h21"
    },
    {
      "type": "Basse",
      "heure": "12h12"
    },
    {
      "type": "Haute",
      "heure": "18h39"
    },
    {
      "type": "Basse",
      "heure": "00h45"
    }
  ],
  "maree_coef": "",
  "maree_coef_am": "",
  "maree_coef_pm": "",
  "drapeau": "nc",
  "surv_label": "Baignade non surveillee",
  "transports": {
    "bayonne": [
      "17:17",
      "17:43",
      "18:27"
    ],
    "dax": [
      "14:57",
      "16:36",
      "17:12"
    ]
  }
}