{
  "updated": "2026-07-12T20:21",
  "temp_air": "25",
  "meteo_picto": "cloud-sun",
  "meteo_label": "Peu nuageux",
  "temp_eau": "NC",
  "vent_kmh": "30",
  "vent_deg": "260",
  "vent_cardinal": "O",
  "uv": "7.0",
  "uv_label": "Eleve",
  "lever": "06:36",
  "coucher": "21:46",
  "houle_m": "0.72",
  "houle_periode": "6.7",
  "marees": [
    {
      "type": "Haute",
      "heure": "03h11"
    },
    {
      "type": "Basse",
      "heure": "09h07"
    },
    {
      "type": "Haute",
      "heure": "15h37"
    },
    {
      "type": "Basse",
      "heure": "21h45"
    }
  ],
  "maree_coef": "65 / 70",
  "maree_coef_am": "65",
  "maree_coef_pm": "70",
  "drapeau": "nc",
  "surv_label": "Baignade non surveillee",
  "transports": {
    "bayonne": [
      "06:15",
      "07:07",
      "08:20"
    ],
    "dax": [
      "07:22",
      "08:14",
      "10:38"
    ]
  },
  "bus": {
    "plage": [
      "06:04+1",
      "07:13+1",
      "07:43+1"
    ],
    "ondres_bourg": [
      "22:46",
      "23:01",
      "23:46"
    ],
    "st_martin": [
      "23:02",
      "23:15"
    ],
    "bayonne": [
      "06:13+1",
      "07:00+1",
      "07:20+1"
    ],
    "fetes_bayonne": []
  }
}